utpgetools/__init__.py
utpgetools/artificial_lift.py
utpgetools/facilities.py
utpgetools/formation_evaluation.py
utpgetools/general.py
utpgetools/geomechanics.py
utpgetools/geostats.py
utpgetools/numerical_methods.py
utpgetools/production.py
utpgetools/res_2.py
utpgetools/utilities_package.py
utpgetools-0.1.3.6.dist-info/licenses/LICENSE.txt
utpgetools-0.1.3.6.dist-info/METADATA
utpgetools-0.1.3.6.dist-info/WHEEL
utpgetools-0.1.3.6.dist-info/top_level.txt
utpgetools-0.1.3.6.dist-info/RECORD
