Metadata-Version: 2.4
Name: utpgetools
Version: 0.1.3.6
Summary: A collection of utility tools for your UT PGE projects.
Home-page: https://github.com/bRunquist/utpgetools
Author: Brecken Runquist
License: Custom Academic Use License
Requires-Python: >=3.7
License-File: LICENSE.txt
Requires-Dist: numpy
Requires-Dist: pandas
Requires-Dist: matplotlib
Requires-Dist: rich
Dynamic: author
Dynamic: home-page
Dynamic: license
Dynamic: license-file
Dynamic: requires-dist
Dynamic: requires-python
Dynamic: summary
